MANIFEST.in
README.txt
setup.py
docs/HISTORY.txt
docs/INSTALL.txt
docs/LICENSE.GPL
docs/LICENSE.txt
redturtle/__init__.py
redturtle.portlet.contextualsearch.egg-info/PKG-INFO
redturtle.portlet.contextualsearch.egg-info/SOURCES.txt
redturtle.portlet.contextualsearch.egg-info/dependency_links.txt
redturtle.portlet.contextualsearch.egg-info/entry_points.txt
redturtle.portlet.contextualsearch.egg-info/namespace_packages.txt
redturtle.portlet.contextualsearch.egg-info/not-zip-safe
redturtle.portlet.contextualsearch.egg-info/requires.txt
redturtle.portlet.contextualsearch.egg-info/top_level.txt
redturtle/portlet/__init__.py
redturtle/portlet/contextualsearch/__init__.py
redturtle/portlet/contextualsearch/configure.zcml
redturtle/portlet/contextualsearch/contextualsearchportlet.pt
redturtle/portlet/contextualsearch/contextualsearchportlet.py
redturtle/portlet/contextualsearch/setuphandlers.py
redturtle/portlet/contextualsearch/skins.zcml
redturtle/portlet/contextualsearch/browser/__init__.py
redturtle/portlet/contextualsearch/browser/configure.zcml
redturtle/portlet/contextualsearch/browser/contextual_search.pt
redturtle/portlet/contextualsearch/browser/stylesheets/contextual_search.css
redturtle/portlet/contextualsearch/locales/it/LC_MESSAGES/redturtle.portlet.contextualsearch.po
redturtle/portlet/contextualsearch/profiles/default/cssregistry.xml
redturtle/portlet/contextualsearch/profiles/default/metadata.xml
redturtle/portlet/contextualsearch/profiles/default/portlets.xml
redturtle/portlet/contextualsearch/profiles/default/registry.xml
redturtle/portlet/contextualsearch/profiles/default/skins.xml
redturtle/portlet/contextualsearch/profiles/mosaic_support/registry.xml
redturtle/portlet/contextualsearch/profiles/uninstall/cssregistry.xml
redturtle/portlet/contextualsearch/profiles/uninstall/registry.xml
redturtle/portlet/contextualsearch/profiles/uninstall/skins.xml
redturtle/portlet/contextualsearch/skins/redturtle_portlet_contextualsearch/contextual_livesearch_reply.py
redturtle/portlet/contextualsearch/tests/__init__.py
redturtle/portlet/contextualsearch/tests/base.py
redturtle/portlet/contextualsearch/tests/test_portlet.py
redturtle/portlet/contextualsearch/tiles/__init__.py
redturtle/portlet/contextualsearch/tiles/configure.zcml
redturtle/portlet/contextualsearch/tiles/content.zcml
redturtle/portlet/contextualsearch/tiles/contextualsearchtile.py
redturtle/portlet/contextualsearch/tiles/templates/contextualsearch_view.pt