Metadata-Version: 1.1
Name: redturtle.portlet.contextualsearch
Version: 2.1.2
Summary: A contextual search portlet
Home-page: http://svn.plone.org/svn/collective/redturtle.portlet.contextualsearch/trunk
Author: RedTurtle Technology
Author-email: sviluppoplone@redturtle.it
License: GPL
Keywords: plone portlet search contextual
Platform: UNKNOWN
Classifier: Framework :: Plone
Classifier: Framework :: Plone :: 4.2
Classifier: Programming Language :: Python
Classifier: Topic :: Software Development :: Libraries :: Python Modules
